setup.py
distributions/Binomialdistribution.py
distributions/Gaussiandistribution.py
distributions/Generaldistribution.py
distributions/__init__.py
dnsd_distributions.egg-info/PKG-INFO
dnsd_distributions.egg-info/SOURCES.txt
dnsd_distributions.egg-info/dependency_links.txt
dnsd_distributions.egg-info/not-zip-safe
dnsd_distributions.egg-info/top_level.txt